aoirint_id3/__init__.py
aoirint_id3/detect.py
aoirint_id3/id3v1.py
aoirint_id3/id3v1_1.py
aoirint_id3/id3v1_genres.csv
aoirint_id3/id3v2_2.py
aoirint_id3/id3v2_2_available_frame_ids.csv
aoirint_id3/id3v2_3.py
aoirint_id3/id3v2_3_available_frame_ids.csv
aoirint_id3/id3v2_3_picture_type_ids.csv
aoirint_id3/utils.py
aoirint_id3-0.1.4.dist-info/LICENSE
aoirint_id3-0.1.4.dist-info/METADATA
aoirint_id3-0.1.4.dist-info/WHEEL
aoirint_id3-0.1.4.dist-info/RECORD
