Metadata-Version: 2.1
Name: aoirint-id3
Version: 0.1.4
Summary: 
Home-page: https://github.com/aoirint/id3py
License: MIT
Author: aoirint
Author-email: aoirint@gmail.com
Requires-Python: >=3.9,<4.0
Classifier: License :: OSI Approved :: MIT License
Classifier: Programming Language :: Python :: 3
Classifier: Programming Language :: Python :: 3.9
Classifier: Programming Language :: Python :: 3.10
Classifier: Programming Language :: Python :: 3.11
Requires-Dist: pydantic (>=1.10.4,<2.0.0)
Project-URL: Repository, https://github.com/aoirint/id3py
